jgtapy/__init__.py
jgtapy/indicators.py
jgtapy/utils.py
jgtapy_beta-1.9.11.dist-info/AUTHORS
jgtapy_beta-1.9.11.dist-info/LICENSE
jgtapy_beta-1.9.11.dist-info/METADATA
jgtapy_beta-1.9.11.dist-info/WHEEL
jgtapy_beta-1.9.11.dist-info/top_level.txt
jgtapy_beta-1.9.11.dist-info/RECORD
