Metadata-Version: 2.1
Name: jgtapy-beta
Version: 1.9.11
Summary: Enhanced Tapy Beta
Home-page: https://github.com/jgwill/jgtapy
Author: Guillaume Isabelle
Author-email: JGWill <jgi@jgwill.com>
License: MIT
Project-URL: Homepage, https://github.com/jgwill/jgtapy
Project-URL: Bug Tracker, https://github.com/users/jgwill/projects/9
Keywords: technical analyse indicators pandas forex stocks
Classifier: Development Status :: 4 - Beta
Classifier: Intended Audience :: System Administrators
Classifier: Programming Language :: Python :: 3
Classifier: License :: OSI Approved :: MIT License
Classifier: Operating System :: OS Independent
Requires-Python: >=3.7
License-File: LICENSE
License-File: AUTHORS
Requires-Dist: pandas (>=0.25.1)
Requires-Dist: tapy (>=1.9.5)
Provides-Extra: dev
Requires-Dist: flake8 (<3.7.0,>=3.6.0) ; extra == 'dev'
Requires-Dist: isort (<4.4.0,>=4.3.4) ; extra == 'dev'
Requires-Dist: coverage ; extra == 'dev'
Requires-Dist: pytest (>=3.10) ; extra == 'dev'
Requires-Dist: readme-renderer ; extra == 'dev'
Requires-Dist: sphinx ; extra == 'dev'
Requires-Dist: sphinx-rtd-theme (>=0.4.0) ; extra == 'dev'
Provides-Extra: dev-docs
Requires-Dist: readme-renderer ; extra == 'dev-docs'
Requires-Dist: sphinx ; extra == 'dev-docs'
Requires-Dist: sphinx-rtd-theme (>=0.4.0) ; extra == 'dev-docs'
Provides-Extra: dev-lint
Requires-Dist: flake8 (<3.7.0,>=3.6.0) ; extra == 'dev-lint'
Requires-Dist: isort (<4.4.0,>=4.3.4) ; extra == 'dev-lint'
Provides-Extra: dev-test
Requires-Dist: coverage ; extra == 'dev-test'
Requires-Dist: pytest (>=3.10) ; extra == 'dev-test'
